tinyllama_cpp/__init__.py
tinyllama_cpp/include/httplib.h
tinyllama_cpp/lib/cmake/httplib/FindBrotli.cmake
tinyllama_cpp/lib/cmake/httplib/httplibConfig.cmake
tinyllama_cpp/lib/cmake/httplib/httplibConfigVersion.cmake
tinyllama_cpp/lib/cmake/httplib/httplibTargets.cmake
tinyllama_cpp/tinyllama_bindings.pyd
tinyllama_cpp-0.0.0.dist-info/METADATA
tinyllama_cpp-0.0.0.dist-info/WHEEL
tinyllama_cpp-0.0.0.dist-info/RECORD
