Metadata-Version: 2.2
Name: tinyllama-cpp
Version: 0.0.0
Summary: Python bindings for the tinyllama.cpp inference engine
Keywords: llm,inference,cpp,tinyllama,language-model
Author-Email: Jonathan Reich <jonathanreich100@gmail.com>
Maintainer-Email: Jonathan Reich <jonathanreich100@gmail.com>
License: MIT
Classifier: Development Status :: 3 - Alpha
Classifier: Intended Audience :: Developers
Classifier: Intended Audience :: Science/Research
Classifier: License :: OSI Approved :: MIT License
Classifier: Programming Language :: Python :: 3
Classifier: Programming Language :: Python :: 3.8
Classifier: Programming Language :: Python :: 3.9
Classifier: Programming Language :: Python :: 3.10
Classifier: Programming Language :: Python :: 3.11
Classifier: Programming Language :: Python :: 3.12
Classifier: Programming Language :: C++
Classifier: Topic :: Scientific/Engineering :: Artificial Intelligence
Classifier: Topic :: Software Development :: Libraries :: Python Modules
Classifier: Operating System :: OS Independent
Project-URL: Homepage, https://github.com/JohnnyTeutonic/tinyllama.cpp
Project-URL: Repository, https://github.com/JohnnyTeutonic/tinyllama.cpp
Project-URL: Documentation, https://github.com/JohnnyTeutonic/tinyllama.cpp#readme
Project-URL: Bug Tracker, https://github.com/JohnnyTeutonic/tinyllama.cpp/issues
Project-URL: Changelog, https://github.com/JohnnyTeutonic/tinyllama.cpp/releases
Requires-Python: >=3.8
Requires-Dist: numpy>=1.19.0
Provides-Extra: torch
Requires-Dist: torch>=1.9.0; extra == "torch"
Requires-Dist: transformers>=4.20.0; extra == "torch"
Requires-Dist: numpy>=1.21.0; extra == "torch"
Requires-Dist: safetensors>=0.3.0; extra == "torch"
